flowity/__init__.py
flowity/parser/__init__.py
flowity/parser/lex.py
flowity/parser/parser.py
flowity/rt/__init__.py
flowity/rt/builtin.py
flowity/rt/context.py
flowity/rt/error.py
flowity/rt/rtime.py
flowity/rt/symbol.py
flowity-0.0.1.dist-info/METADATA
flowity-0.0.1.dist-info/WHEEL
flowity-0.0.1.dist-info/top_level.txt
flowity-0.0.1.dist-info/RECORD
