Metadata-Version: 2.1
Name: flowity
Version: 0.0.1
Summary: Workflow language designed for LLM.
Home-page: https://github.com/RockChinQ/Flowity
Author: RockChinQ
Author-email: junyan_qin@qq.com
Project-URL: Bug Report, https://github.com/RockChinQ/Flowity/issues
Classifier: Intended Audience :: Developers
Classifier: Intended Audience :: End Users/Desktop
Classifier: Natural Language :: English
Classifier: Topic :: Software Development :: Libraries :: Python Modules
Classifier: Programming Language :: Python :: 3
Classifier: Programming Language :: Python :: 3.9
Classifier: Programming Language :: Python :: 3.10
Classifier: Programming Language :: Python :: 3.11
Classifier: Programming Language :: Python :: 3.12
Classifier: Operating System :: OS Independent
Requires-Dist: langchain
Requires-Dist: langchain-openai
Requires-Dist: pydantic
Requires-Dist: ply
